amipwnd/__init__.py
amipwnd/amipwnd.py
amipwnd/amipwnd_cli.py
amipwnd-0.1.7.dist-info/METADATA
amipwnd-0.1.7.dist-info/WHEEL
amipwnd-0.1.7.dist-info/entry_points.txt
amipwnd-0.1.7.dist-info/top_level.txt
amipwnd-0.1.7.dist-info/RECORD
