Metadata-Version: 2.1
Name: amipwnd
Version: 0.1.7
Summary: UNKNOWN
Home-page: UNKNOWN
Author: UNKNOWN
Author-email: UNKNOWN
License: UNKNOWN
Platform: UNKNOWN
Requires-Dist: Click
Requires-Dist: ascii-graph
Requires-Dist: requests
Requires-Dist: tqdm
